ufl/__init__.py
ufl/algebra.py
ufl/argument.py
ufl/assertions.py
ufl/averaging.py
ufl/cell.py
ufl/checks.py
ufl/classes.py
ufl/coefficient.py
ufl/compound_expressions.py
ufl/conditional.py
ufl/constant.py
ufl/constantvalue.py
ufl/differentiation.py
ufl/domain.py
ufl/equation.py
ufl/exprcontainers.py
ufl/exprequals.py
ufl/exproperators.py
ufl/form.py
ufl/formoperators.py
ufl/functionspace.py
ufl/geometry.py
ufl/index_combination_utils.py
ufl/indexed.py
ufl/indexsum.py
ufl/integral.py
ufl/log.py
ufl/mathfunctions.py
ufl/measure.py
ufl/measureoperators.py
ufl/objects.py
ufl/operators.py
ufl/permutation.py
ufl/precedence.py
ufl/protocols.py
ufl/referencevalue.py
ufl/restriction.py
ufl/sobolevspace.py
ufl/sorting.py
ufl/split_functions.py
ufl/tensoralgebra.py
ufl/tensors.py
ufl/variable.py
ufl/algorithms/__init__.py
ufl/algorithms/ad.py
ufl/algorithms/analysis.py
ufl/algorithms/apply_algebra_lowering.py
ufl/algorithms/apply_derivatives.py
ufl/algorithms/apply_function_pullbacks.py
ufl/algorithms/apply_geometry_lowering.py
ufl/algorithms/apply_integral_scaling.py
ufl/algorithms/apply_restrictions.py
ufl/algorithms/balancing.py
ufl/algorithms/change_to_reference.py
ufl/algorithms/check_arities.py
ufl/algorithms/check_restrictions.py
ufl/algorithms/checks.py
ufl/algorithms/comparison_checker.py
ufl/algorithms/compute_form_data.py
ufl/algorithms/coordinate_derivative_helpers.py
ufl/algorithms/domain_analysis.py
ufl/algorithms/elementtransformations.py
ufl/algorithms/estimate_degrees.py
ufl/algorithms/expand_compounds.py
ufl/algorithms/expand_indices.py
ufl/algorithms/formdata.py
ufl/algorithms/formfiles.py
ufl/algorithms/formsplitter.py
ufl/algorithms/formtransformations.py
ufl/algorithms/map_integrands.py
ufl/algorithms/multifunction.py
ufl/algorithms/preprocess_expression.py
ufl/algorithms/remove_complex_nodes.py
ufl/algorithms/renumbering.py
ufl/algorithms/replace.py
ufl/algorithms/signature.py
ufl/algorithms/transformer.py
ufl/algorithms/traversal.py
dev_fenics_ufl-2021.1.1.dist-info/AUTHORS
dev_fenics_ufl-2021.1.1.dist-info/COPYING
dev_fenics_ufl-2021.1.1.dist-info/COPYING.LESSER
dev_fenics_ufl-2021.1.1.dist-info/METADATA
dev_fenics_ufl-2021.1.1.dist-info/WHEEL
dev_fenics_ufl-2021.1.1.dist-info/top_level.txt
dev_fenics_ufl-2021.1.1.dist-info/RECORD
